AUTHORS
CHANGELOG.txt
DESCRIPTION
LICENSE
MANIFEST.in
README.rst
setup.cfg
setup.py
cmsplugin_accordion/__init__.py
cmsplugin_accordion/admin.py
cmsplugin_accordion/cms_plugins.py
cmsplugin_accordion/forms.py
cmsplugin_accordion/models.py
cmsplugin_accordion/urls.py
cmsplugin_accordion/views.py
cmsplugin_accordion.egg-info/PKG-INFO
cmsplugin_accordion.egg-info/SOURCES.txt
cmsplugin_accordion.egg-info/dependency_links.txt
cmsplugin_accordion.egg-info/requires.txt
cmsplugin_accordion.egg-info/top_level.txt
cmsplugin_accordion/migrations/0001_initial.py
cmsplugin_accordion/migrations/__init__.py
cmsplugin_accordion/templates/cmsplugin_accordion/.empty
cmsplugin_accordion/templates/cmsplugin_accordion/accordion_plugin.html
cmsplugin_accordion/templates/cmsplugin_accordion/plugin_change_form.html
cmsplugin_accordion/tests/.coverage
cmsplugin_accordion/tests/.coveragerc
cmsplugin_accordion/tests/__init__.py
cmsplugin_accordion/tests/cms_plugins_tests.py
cmsplugin_accordion/tests/factories.py
cmsplugin_accordion/tests/models_tests.py
cmsplugin_accordion/tests/runtests.py
cmsplugin_accordion/tests/south_settings.py
cmsplugin_accordion/tests/test_settings.py
cmsplugin_accordion/tests/urls.py
cmsplugin_accordion/tests/test_app/__init__.py
cmsplugin_accordion/tests/test_app/models.py
cmsplugin_accordion/tests/test_app/templates/400.html
cmsplugin_accordion/tests/test_app/templates/500.html
cmsplugin_accordion/tests/test_app/templates/base.html
cmsplugin_accordion/tests/test_app/templates/default.html