Metadata-Version: 1.0
Name: cmsplugin-accordion
Version: 0.2.2
Summary: django-cms plugin that allow to create accordions on the frontend.
